openpibo/__init__.py
openpibo/audio.py
openpibo/collect.py
openpibo/device.py
openpibo/motion.py
openpibo/oled.py
openpibo/speech.py
openpibo/vision.py
openpibo/modules/__init__.py
openpibo/modules/card/__init__.py
openpibo/modules/card/decode_card.py
openpibo/modules/oled/__init__.py
openpibo/modules/oled/board.py
openpibo/modules/oled/busio.py
openpibo/modules/oled/chip.py
openpibo/modules/oled/digitalio.py
openpibo/modules/oled/framebuf.py
openpibo/modules/oled/ili9341.py
openpibo/modules/oled/pure_spi.py
openpibo/modules/oled/rgb.py
openpibo/modules/oled/spi.py
openpibo/modules/oled/spi_device.py
openpibo/modules/oled/ssd1306.py
openpibo/modules/oled/st7735.py
openpibo/modules/oled/util.py
openpibo/modules/pose/__init__.py
openpibo/modules/pose/data.py
openpibo/modules/pose/movenet.py
openpibo/modules/pose/utils.py
openpibo/modules/speech/__init__.py
openpibo/modules/speech/constant.py
openpibo/modules/speech/mtranslate.py
openpibo_python-0.9.2.74.dist-info/METADATA
openpibo_python-0.9.2.74.dist-info/WHEEL
openpibo_python-0.9.2.74.dist-info/top_level.txt
openpibo_python-0.9.2.74.dist-info/RECORD
