Metadata-Version: 2.1
Name: openpibo-python
Version: 0.9.2.74
Summary: openpibo-python package.
Home-page: https://github.com/themakerrobot/openpibo-python
Author: circulus
Author-email: leeyunjai@circul.us
License: UNKNOWN
Keywords: openpibo
Platform: UNKNOWN
Classifier: Natural Language :: English
Classifier: Programming Language :: Python :: 3.5
Classifier: Programming Language :: Python :: 3.6
Classifier: Programming Language :: Python :: 3.7
Classifier: Programming Language :: Python :: 3.8
Requires-Dist: opencv-contrib-python (>=4.5.4.60)
Requires-Dist: dlib (>=19.24.0)
Requires-Dist: pyzbar (>=0.1.8)
Requires-Dist: beautifulsoup4 (>=4.6.0)
Requires-Dist: konlpy (>=0.5.2)
Requires-Dist: tweepy (>=3.10.0)
Requires-Dist: future (>=0.18.2)
Requires-Dist: pillow (>=7.2.0)
Requires-Dist: RPi.gpio (>=0.7.0)
Requires-Dist: pyserial (>=3.5)
Requires-Dist: requests (>=2.28.1)
Requires-Dist: tflite-runtime (>=2.5.0)
Requires-Dist: openpibo-models (>=0.4.7)
Requires-Dist: openpibo-face-models (>=0.4.3)
Requires-Dist: openpibo-detect-models (>=0.4.4)
Requires-Dist: openpibo-dlib-models (>=0.4.2)
